{
  "annotations": {
    "list": [
      {
        "builtIn": 1,
        "datasource": "-- Grafana --",
        "enable": true,
        "hide": true,
        "iconColor": "rgba(0, 211, 255, 1)",
        "name": "Annotations & Alerts",
        "type": "dashboard"
      }
    ]
  },
  "editable": true,
  "gnetId": null,
  "graphTooltip": 1,
  "id": null,
  "iteration": 1534201384553,
  "links": [
    {
      "icon": "external link",
      "tags": [],
      "targetBlank": true,
      "title": "linkerd.io",
      "type": "link",
      "url": "https://linkerd.io"
    }
  ],
  "panels": [
    {
      "content": "<div>\n  <div style=\"position: absolute; bottom: 0\">\n    <a href=\"https://linkerd.io\" target=\"_blank\"><img src=\"https://linkerd.io/images/logo-100h.png\" style=\"height: 40px;\"></a>\n  </div>\n  <div style=\"position: absolute; bottom: 0; right: 0; font-size: 15px\">\n    linkerd enables\n    <a href=\"https://linkerd.io/in-depth/concepts/#service-discovery\" target=\"_blank\">service discovery</a>,\n    <a href=\"https://linkerd.io/in-depth/routing/\" target=\"_blank\">routing</a>, and\n    <a href=\"https://linkerd.io/in-depth/routing/#load-balancing\" target=\"_blank\">load balancing</a>.\n    <a href=\"https://linkerd.io/getting-started/\" target=\"_blank\">Learn more &raquo;</a>\n    <br>\n    Need help? Join us on <a href=\"http://slack.linkerd.io\" target=\"_blank\">the linkerd Slack</a>.\n  </div>\n</div>\n",
      "editable": true,
      "error": false,
      "gridPos": {
        "h": 3,
        "w": 24,
        "x": 0,
        "y": 0
      },
      "id": 20,
      "links": [],
      "mode": "html",
      "title": "",
      "transparent": true,
      "type": "text"
    },
    {
      "cacheTimeout": null,
      "colorBackground": false,
      "colorValue": false,
      "colors": [
        "rgba(245, 54, 54, 0.9)",
        "rgba(237, 129, 40, 0.89)",
        "rgba(50, 172, 45, 0.97)"
      ],
      "datasource": "prometheus",
      "editable": true,
      "error": false,
      "format": "none",
      "gauge": {
        "maxValue": 100,
        "minValue": 0,
        "show": false,
        "thresholdLabels": false,
        "thresholdMarkers": true
      },
      "gridPos": {
        "h": 4,
        "w": 6,
        "x": 0,
        "y": 3
      },
      "id": 49,
      "interval": null,
      "links": [],
      "mappingType": 1,
      "mappingTypes": [
        {
          "name": "value to text",
          "value": 1
        },
        {
          "name": "range to text",
          "value": 2
        }
      ],
      "maxDataPoints": 100,
      "minSpan": 4,
      "nullPointMode": "connected",
      "nullText": null,
      "postfix": "",
      "postfixFontSize": "50%",
      "prefix": "",
      "prefixFontSize": "50%",
      "rangeMaps": [
        {
          "from": "null",
          "text": "N/A",
          "to": "null"
        }
      ],
      "sparkline": {
        "fillColor": "rgba(31, 118, 189, 0.18)",
        "full": false,
        "lineColor": "rgb(31, 120, 193)",
        "show": false
      },
      "tableColumn": "",
      "targets": [
        {
          "expr": "count(count(jvm:uptime) by(instance))",
          "intervalFactor": 1,
          "legendFormat": "",
          "refId": "A",
          "step": 4
        }
      ],
      "thresholds": "",
      "title": "linkerd Instances",
      "transparent": false,
      "type": "singlestat",
      "valueFontSize": "150%",
      "valueMaps": [
        {
          "op": "=",
          "text": "N/A",
          "value": "null"
        }
      ],
      "valueName": "current"
    },
    {
      "cacheTimeout": null,
      "colorBackground": false,
      "colorValue": false,
      "colors": [
        "rgba(245, 54, 54, 0.9)",
        "rgba(237, 129, 40, 0.89)",
        "rgba(50, 172, 45, 0.97)"
      ],
      "datasource": "prometheus",
      "decimals": null,
      "editable": true,
      "error": false,
      "format": "ms",
      "gauge": {
        "maxValue": 100,
        "minValue": 0,
        "show": false,
        "thresholdLabels": false,
        "thresholdMarkers": true
      },
      "gridPos": {
        "h": 4,
        "w": 6,
        "x": 6,
        "y": 3
      },
      "id": 51,
      "interval": null,
      "links": [],
      "mappingType": 1,
      "mappingTypes": [
        {
          "name": "value to text",
          "value": 1
        },
        {
          "name": "range to text",
          "value": 2
        }
      ],
      "maxDataPoints": 100,
      "nullPointMode": "connected",
      "nullText": null,
      "postfix": "",
      "postfixFontSize": "50%",
      "prefix": "",
      "prefixFontSize": "50%",
      "rangeMaps": [
        {
          "from": "null",
          "text": "N/A",
          "to": "null"
        }
      ],
      "sparkline": {
        "fillColor": "rgba(31, 118, 189, 0.18)",
        "full": true,
        "lineColor": "rgb(31, 120, 193)",
        "show": true
      },
      "tableColumn": "",
      "targets": [
        {
          "expr": "avg(jvm:uptime)",
          "intervalFactor": 1,
          "legendFormat": "",
          "refId": "A",
          "step": 4
        }
      ],
      "thresholds": "",
      "title": "Average Uptime",
      "type": "singlestat",
      "valueFontSize": "70%",
      "valueMaps": [
        {
          "op": "=",
          "text": "N/A",
          "value": "null"
        }
      ],
      "valueName": "current"
    },
    {
      "cacheTimeout": null,
      "colorBackground": false,
      "colorValue": false,
      "colors": [
        "rgba(245, 54, 54, 0.9)",
        "rgba(237, 129, 40, 0.89)",
        "rgba(50, 172, 45, 0.97)"
      ],
      "datasource": "prometheus",
      "editable": true,
      "error": false,
      "format": "none",
      "gauge": {
        "maxValue": 100,
        "minValue": 0,
        "show": false,
        "thresholdLabels": false,
        "thresholdMarkers": true
      },
      "gridPos": {
        "h": 4,
        "w": 6,
        "x": 12,
        "y": 3
      },
      "id": 53,
      "interval": null,
      "links": [],
      "mappingType": 1,
      "mappingTypes": [
        {
          "name": "value to text",
          "value": 1
        },
        {
          "name": "range to text",
          "value": 2
        }
      ],
      "maxDataPoints": 100,
      "minSpan": 4,
      "nullPointMode": "connected",
      "nullText": null,
      "postfix": " CPUs",
      "postfixFontSize": "50%",
      "prefix": "",
      "prefixFontSize": "50%",
      "rangeMaps": [
        {
          "from": "null",
          "text": "N/A",
          "to": "null"
        }
      ],
      "sparkline": {
        "fillColor": "rgba(31, 118, 189, 0.18)",
        "full": true,
        "lineColor": "rgb(31, 120, 193)",
        "show": true
      },
      "tableColumn": "",
      "targets": [
        {
          "expr": "sum(jvm:num_cpus)",
          "intervalFactor": 1,
          "legendFormat": "",
          "refId": "A",
          "step": 4
        }
      ],
      "thresholds": "",
      "title": "Global CPUs Available",
      "type": "singlestat",
      "valueFontSize": "70%",
      "valueMaps": [
        {
          "op": "=",
          "text": "N/A",
          "value": "null"
        }
      ],
      "valueName": "current"
    },
    {
      "cacheTimeout": null,
      "colorBackground": false,
      "colorValue": true,
      "colors": [
        "rgba(50, 172, 45, 0.97)",
        "rgba(237, 129, 40, 0.89)",
        "rgba(245, 54, 54, 0.9)"
      ],
      "datasource": "prometheus",
      "editable": true,
      "error": false,
      "format": "percentunit",
      "gauge": {
        "maxValue": 1,
        "minValue": 0,
        "show": true,
        "thresholdLabels": false,
        "thresholdMarkers": true
      },
      "gridPos": {
        "h": 4,
        "w": 6,
        "x": 18,
        "y": 3
      },
      "id": 52,
      "interval": null,
      "links": [],
      "mappingType": 1,
      "mappingTypes": [
        {
          "name": "value to text",
          "value": 1
        },
        {
          "name": "range to text",
          "value": 2
        }
      ],
      "maxDataPoints": 100,
      "minSpan": 4,
      "nullPointMode": "connected",
      "nullText": null,
      "postfix": "",
      "postfixFontSize": "50%",
      "prefix": "",
      "prefixFontSize": "50%",
      "rangeMaps": [
        {
          "from": "null",
          "text": "N/A",
          "to": "null"
        }
      ],
      "sparkline": {
        "fillColor": "rgba(31, 118, 189, 0.18)",
        "full": true,
        "lineColor": "rgb(31, 120, 193)",
        "show": true
      },
      "tableColumn": "",
      "targets": [
        {
          "expr": "sum(jvm:heap:used)/sum(jvm:heap:max)",
          "format": "time_series",
          "intervalFactor": 1,
          "legendFormat": "",
          "refId": "A",
          "step": 4
        }
      ],
      "thresholds": "0.8,0.9",
      "title": "Global Memory Usage",
      "type": "singlestat",
      "valueFontSize": "70%",
      "valueMaps": [
        {
          "op": "=",
          "text": "N/A",
          "value": "null"
        }
      ],
      "valueName": "current"
    },
    {
      "content": "<div class=\"text-center dashboard-header\">\n  <span>GC</span>\n</div>\n",
      "editable": true,
      "error": false,
      "gridPos": {
        "h": 3,
        "w": 24,
        "x": 0,
        "y": 7
      },
      "height": "1px",
      "id": 75,
      "links": [],
      "minSpan": 24,
      "mode": "html",
      "title": "",
      "transparent": true,
      "type": "text"
    },
    {
      "aliasColors": {},
      "bars": false,
      "dashLength": 10,
      "dashes": false,
      "datasource": "prometheus",
      "decimals": null,
      "editable": true,
      "error": false,
      "fill": 1,
      "grid": {},
      "gridPos": {
        "h": 7,
        "w": 8,
        "x": 0,
        "y": 10
      },
      "id": 59,
      "legend": {
        "avg": false,
        "current": false,
        "max": false,
        "min": false,
        "show": false,
        "total": false,
        "values": false
      },
      "lines": true,
      "linewidth": 2,
      "links": [],
      "minSpan": 8,
      "nullPointMode": "connected",
      "percentage": false,
      "pointradius": 5,
      "points": false,
      "renderer": "flot",
      "seriesOverrides": [],
      "spaceLength": 10,
      "stack": false,
      "steppedLine": false,
      "targets": [
        {
          "expr": "irate(jvm:gc:cycles{instance=~\"$instance\"}[1m])",
          "intervalFactor": 1,
          "legendFormat": "{{instance}}",
          "refId": "A",
          "step": 2
        }
      ],
      "thresholds": [],
      "timeFrom": null,
      "timeShift": null,
      "title": "Cycles (Total)",
      "tooltip": {
        "msResolution": false,
        "shared": true,
        "sort": 2,
        "value_type": "cumulative"
      },
      "type": "graph",
      "xaxis": {
        "buckets": null,
        "mode": "time",
        "name": null,
        "show": true,
        "values": []
      },
      "yaxes": [
        {
          "format": "none",
          "label": "",
          "logBase": 1,
          "max": null,
          "min": null,
          "show": true
        },
        {
          "format": "short",
          "label": null,
          "logBase": 1,
          "max": null,
          "min": null,
          "show": false
        }
      ],
      "yaxis": {
        "align": false,
        "alignLevel": null
      }
    },
    {
      "aliasColors": {},
      "bars": false,
      "dashLength": 10,
      "dashes": false,
      "datasource": "prometheus",
      "decimals": null,
      "editable": true,
      "error": false,
      "fill": 1,
      "grid": {},
      "gridPos": {
        "h": 7,
        "w": 8,
        "x": 8,
        "y": 10
      },
      "id": 72,
      "legend": {
        "avg": false,
        "current": false,
        "max": false,
        "min": false,
        "show": false,
        "total": false,
        "values": false
      },
      "lines": true,
      "linewidth": 2,
      "links": [],
      "minSpan": 8,
      "nullPointMode": "connected",
      "percentage": false,
      "pointradius": 5,
      "points": false,
      "renderer": "flot",
      "seriesOverrides": [],
      "spaceLength": 10,
      "stack": false,
      "steppedLine": false,
      "targets": [
        {
          "expr": "irate(jvm:gc:ConcurrentMarkSweep:cycles{instance=~\"$instance\"}[1m])",
          "intervalFactor": 1,
          "legendFormat": "{{instance}}",
          "metric": "",
          "refId": "A",
          "step": 2
        }
      ],
      "thresholds": [],
      "timeFrom": null,
      "timeShift": null,
      "title": "Cycles (CMS)",
      "tooltip": {
        "msResolution": false,
        "shared": true,
        "sort": 2,
        "value_type": "cumulative"
      },
      "type": "graph",
      "xaxis": {
        "buckets": null,
        "mode": "time",
        "name": null,
        "show": true,
        "values": []
      },
      "yaxes": [
        {
          "format": "none",
          "label": "",
          "logBase": 1,
          "max": null,
          "min": null,
          "show": true
        },
        {
          "format": "short",
          "label": null,
          "logBase": 1,
          "max": null,
          "min": null,
          "show": false
        }
      ],
      "yaxis": {
        "align": false,
        "alignLevel": null
      }
    },
    {
      "aliasColors": {},
      "bars": false,
      "dashLength": 10,
      "dashes": false,
      "datasource": "prometheus",
      "decimals": null,
      "editable": true,
      "error": false,
      "fill": 1,
      "grid": {},
      "gridPos": {
        "h": 7,
        "w": 8,
        "x": 16,
        "y": 10
      },
      "id": 74,
      "legend": {
        "avg": false,
        "current": false,
        "max": false,
        "min": false,
        "show": false,
        "total": false,
        "values": false
      },
      "lines": true,
      "linewidth": 2,
      "links": [],
      "minSpan": 8,
      "nullPointMode": "connected",
      "percentage": false,
      "pointradius": 5,
      "points": false,
      "renderer": "flot",
      "seriesOverrides": [],
      "spaceLength": 10,
      "stack": false,
      "steppedLine": false,
      "targets": [
        {
          "expr": "irate(jvm:gc:ParNew:cycles{instance=~\"$instance\"}[1m])",
          "intervalFactor": 1,
          "legendFormat": "{{instance}}",
          "metric": "",
          "refId": "A",
          "step": 2
        }
      ],
      "thresholds": [],
      "timeFrom": null,
      "timeShift": null,
      "title": "Cycles (ParNew)",
      "tooltip": {
        "msResolution": false,
        "shared": true,
        "sort": 2,
        "value_type": "cumulative"
      },
      "type": "graph",
      "xaxis": {
        "buckets": null,
        "mode": "time",
        "name": null,
        "show": true,
        "values": []
      },
      "yaxes": [
        {
          "format": "none",
          "label": "",
          "logBase": 1,
          "max": null,
          "min": null,
          "show": true
        },
        {
          "format": "short",
          "label": null,
          "logBase": 1,
          "max": null,
          "min": null,
          "show": false
        }
      ],
      "yaxis": {
        "align": false,
        "alignLevel": null
      }
    },
    {
      "aliasColors": {},
      "bars": false,
      "dashLength": 10,
      "dashes": false,
      "datasource": "prometheus",
      "decimals": null,
      "editable": true,
      "error": false,
      "fill": 1,
      "grid": {},
      "gridPos": {
        "h": 7,
        "w": 8,
        "x": 0,
        "y": 17
      },
      "id": 61,
      "legend": {
        "avg": false,
        "current": false,
        "max": false,
        "min": false,
        "show": false,
        "total": false,
        "values": false
      },
      "lines": true,
      "linewidth": 2,
      "links": [],
      "minSpan": 8,
      "nullPointMode": "connected",
      "percentage": false,
      "pointradius": 5,
      "points": false,
      "renderer": "flot",
      "seriesOverrides": [],
      "spaceLength": 10,
      "stack": false,
      "steppedLine": false,
      "targets": [
        {
          "expr": "irate(jvm:gc:msec{instance=~\"$instance\"}[1m])",
          "intervalFactor": 1,
          "legendFormat": "{{instance}}",
          "metric": "",
          "refId": "A",
          "step": 2
        }
      ],
      "thresholds": [],
      "timeFrom": null,
      "timeShift": null,
      "title": "Time spent (Total)",
      "tooltip": {
        "msResolution": false,
        "shared": true,
        "sort": 2,
        "value_type": "cumulative"
      },
      "type": "graph",
      "xaxis": {
        "buckets": null,
        "mode": "time",
        "name": null,
        "show": true,
        "values": []
      },
      "yaxes": [
        {
          "format": "ms",
          "label": "",
          "logBase": 1,
          "max": null,
          "min": null,
          "show": true
        },
        {
          "format": "short",
          "label": null,
          "logBase": 1,
          "max": null,
          "min": null,
          "show": false
        }
      ],
      "yaxis": {
        "align": false,
        "alignLevel": null
      }
    },
    {
      "aliasColors": {},
      "bars": false,
      "dashLength": 10,
      "dashes": false,
      "datasource": "prometheus",
      "decimals": null,
      "editable": true,
      "error": false,
      "fill": 1,
      "grid": {},
      "gridPos": {
        "h": 7,
        "w": 8,
        "x": 8,
        "y": 17
      },
      "id": 71,
      "legend": {
        "avg": false,
        "current": false,
        "max": false,
        "min": false,
        "show": false,
        "total": false,
        "values": false
      },
      "lines": true,
      "linewidth": 2,
      "links": [],
      "minSpan": 8,
      "nullPointMode": "connected",
      "percentage": false,
      "pointradius": 5,
      "points": false,
      "renderer": "flot",
      "seriesOverrides": [],
      "spaceLength": 10,
      "stack": false,
      "steppedLine": false,
      "targets": [
        {
          "expr": "irate(jvm:gc:ConcurrentMarkSweep:msec{instance=~\"$instance\"}[1m])",
          "intervalFactor": 1,
          "legendFormat": "{{instance}}",
          "metric": "",
          "refId": "A",
          "step": 2
        }
      ],
      "thresholds": [],
      "timeFrom": null,
      "timeShift": null,
      "title": "Time Spent (CMS)",
      "tooltip": {
        "msResolution": false,
        "shared": true,
        "sort": 2,
        "value_type": "cumulative"
      },
      "type": "graph",
      "xaxis": {
        "buckets": null,
        "mode": "time",
        "name": null,
        "show": true,
        "values": []
      },
      "yaxes": [
        {
          "format": "ms",
          "label": "",
          "logBase": 1,
          "max": null,
          "min": null,
          "show": true
        },
        {
          "format": "short",
          "label": null,
          "logBase": 1,
          "max": null,
          "min": null,
          "show": false
        }
      ],
      "yaxis": {
        "align": false,
        "alignLevel": null
      }
    },
    {
      "aliasColors": {},
      "bars": false,
      "dashLength": 10,
      "dashes": false,
      "datasource": "prometheus",
      "decimals": null,
      "editable": true,
      "error": false,
      "fill": 1,
      "grid": {},
      "gridPos": {
        "h": 7,
        "w": 8,
        "x": 16,
        "y": 17
      },
      "id": 73,
      "legend": {
        "avg": false,
        "current": false,
        "max": false,
        "min": false,
        "show": false,
        "total": false,
        "values": false
      },
      "lines": true,
      "linewidth": 2,
      "links": [],
      "minSpan": 8,
      "nullPointMode": "connected",
      "percentage": false,
      "pointradius": 5,
      "points": false,
      "renderer": "flot",
      "seriesOverrides": [],
      "spaceLength": 10,
      "stack": false,
      "steppedLine": false,
      "targets": [
        {
          "expr": "irate(jvm:gc:ParNew:msec{instance=~\"$instance\"}[1m])",
          "intervalFactor": 1,
          "legendFormat": "{{instance}}",
          "metric": "",
          "refId": "A",
          "step": 2
        }
      ],
      "thresholds": [],
      "timeFrom": null,
      "timeShift": null,
      "title": "Time Spent (ParNew)",
      "tooltip": {
        "msResolution": false,
        "shared": true,
        "sort": 2,
        "value_type": "cumulative"
      },
      "type": "graph",
      "xaxis": {
        "buckets": null,
        "mode": "time",
        "name": null,
        "show": true,
        "values": []
      },
      "yaxes": [
        {
          "format": "ms",
          "label": "",
          "logBase": 1,
          "max": null,
          "min": null,
          "show": true
        },
        {
          "format": "short",
          "label": null,
          "logBase": 1,
          "max": null,
          "min": null,
          "show": false
        }
      ],
      "yaxis": {
        "align": false,
        "alignLevel": null
      }
    },
    {
      "content": "<div class=\"text-center dashboard-header\">\n  <span>Memory Usage by Generation</span>\n</div>\n",
      "editable": true,
      "error": false,
      "gridPos": {
        "h": 3,
        "w": 24,
        "x": 0,
        "y": 24
      },
      "height": "1px",
      "id": 68,
      "links": [],
      "minSpan": 24,
      "mode": "html",
      "title": "",
      "transparent": true,
      "type": "text"
    },
    {
      "aliasColors": {},
      "bars": false,
      "dashLength": 10,
      "dashes": false,
      "datasource": "prometheus",
      "decimals": null,
      "editable": true,
      "error": false,
      "fill": 1,
      "grid": {},
      "gridPos": {
        "h": 7,
        "w": 8,
        "x": 0,
        "y": 27
      },
      "id": 65,
      "legend": {
        "alignAsTable": false,
        "avg": false,
        "current": false,
        "hideEmpty": false,
        "hideZero": false,
        "max": false,
        "min": false,
        "rightSide": false,
        "show": false,
        "total": false,
        "values": false
      },
      "lines": true,
      "linewidth": 2,
      "links": [],
      "minSpan": 8,
      "nullPointMode": "connected",
      "percentage": false,
      "pointradius": 5,
      "points": false,
      "renderer": "flot",
      "repeatIteration": 1501718943622,
      "seriesOverrides": [],
      "spaceLength": 10,
      "stack": false,
      "steppedLine": false,
      "targets": [
        {
          "expr": "jvm:mem:current:Par_Eden_Space:used{instance=~\"$instance\"}",
          "intervalFactor": 1,
          "legendFormat": "{{instance}}",
          "metric": "",
          "refId": "A",
          "step": 2
        }
      ],
      "thresholds": [],
      "timeFrom": null,
      "timeShift": null,
      "title": "Eden",
      "tooltip": {
        "msResolution": false,
        "shared": true,
        "sort": 2,
        "value_type": "individual"
      },
      "type": "graph",
      "xaxis": {
        "buckets": null,
        "mode": "time",
        "name": null,
        "show": true,
        "values": []
      },
      "yaxes": [
        {
          "format": "bytes",
          "label": "",
          "logBase": 1,
          "max": null,
          "min": null,
          "show": true
        },
        {
          "format": "short",
          "label": null,
          "logBase": 1,
          "max": null,
          "min": null,
          "show": false
        }
      ],
      "yaxis": {
        "align": false,
        "alignLevel": null
      }
    },
    {
      "aliasColors": {},
      "bars": false,
      "dashLength": 10,
      "dashes": false,
      "datasource": "prometheus",
      "decimals": null,
      "editable": true,
      "error": false,
      "fill": 1,
      "grid": {},
      "gridPos": {
        "h": 7,
        "w": 8,
        "x": 8,
        "y": 27
      },
      "id": 66,
      "legend": {
        "alignAsTable": false,
        "avg": false,
        "current": false,
        "hideEmpty": false,
        "hideZero": false,
        "max": false,
        "min": false,
        "rightSide": false,
        "show": false,
        "total": false,
        "values": false
      },
      "lines": true,
      "linewidth": 2,
      "links": [],
      "minSpan": 8,
      "nullPointMode": "connected",
      "percentage": false,
      "pointradius": 5,
      "points": false,
      "renderer": "flot",
      "seriesOverrides": [],
      "spaceLength": 10,
      "stack": false,
      "steppedLine": false,
      "targets": [
        {
          "expr": "jvm:mem:current:Par_Survivor_Space:used{instance=~\"$instance\"}",
          "intervalFactor": 1,
          "legendFormat": "{{instance}}",
          "metric": "",
          "refId": "A",
          "step": 2
        }
      ],
      "thresholds": [],
      "timeFrom": null,
      "timeShift": null,
      "title": "Survivor",
      "tooltip": {
        "msResolution": false,
        "shared": true,
        "sort": 2,
        "value_type": "individual"
      },
      "type": "graph",
      "xaxis": {
        "buckets": null,
        "mode": "time",
        "name": null,
        "show": true,
        "values": []
      },
      "yaxes": [
        {
          "format": "bytes",
          "label": "",
          "logBase": 1,
          "max": null,
          "min": null,
          "show": true
        },
        {
          "format": "short",
          "label": null,
          "logBase": 1,
          "max": null,
          "min": null,
          "show": false
        }
      ],
      "yaxis": {
        "align": false,
        "alignLevel": null
      }
    },
    {
      "aliasColors": {},
      "bars": false,
      "dashLength": 10,
      "dashes": false,
      "datasource": "prometheus",
      "decimals": null,
      "editable": true,
      "error": false,
      "fill": 1,
      "grid": {},
      "gridPos": {
        "h": 7,
        "w": 8,
        "x": 16,
        "y": 27
      },
      "id": 67,
      "legend": {
        "alignAsTable": false,
        "avg": false,
        "current": false,
        "hideEmpty": false,
        "hideZero": false,
        "max": false,
        "min": false,
        "rightSide": false,
        "show": false,
        "total": false,
        "values": false
      },
      "lines": true,
      "linewidth": 2,
      "links": [],
      "minSpan": 8,
      "nullPointMode": "connected",
      "percentage": false,
      "pointradius": 5,
      "points": false,
      "renderer": "flot",
      "seriesOverrides": [],
      "spaceLength": 10,
      "stack": false,
      "steppedLine": false,
      "targets": [
        {
          "expr": "jvm:mem:current:CMS_Old_Gen:used{instance=~\"$instance\"}",
          "intervalFactor": 1,
          "legendFormat": "{{instance}}",
          "metric": "",
          "refId": "A",
          "step": 2
        }
      ],
      "thresholds": [],
      "timeFrom": null,
      "timeShift": null,
      "title": "Old Gen",
      "tooltip": {
        "msResolution": false,
        "shared": true,
        "sort": 2,
        "value_type": "individual"
      },
      "type": "graph",
      "xaxis": {
        "buckets": null,
        "mode": "time",
        "name": null,
        "show": true,
        "values": []
      },
      "yaxes": [
        {
          "format": "bytes",
          "label": "",
          "logBase": 1,
          "max": null,
          "min": null,
          "show": true
        },
        {
          "format": "short",
          "label": null,
          "logBase": 1,
          "max": null,
          "min": null,
          "show": false
        }
      ],
      "yaxis": {
        "align": false,
        "alignLevel": null
      }
    },
    {
      "content": "<div class=\"text-center dashboard-header\">\n  <span>MEMORY</span>\n</div>\n",
      "editable": true,
      "error": false,
      "gridPos": {
        "h": 3,
        "w": 24,
        "x": 0,
        "y": 34
      },
      "height": "1px",
      "id": 56,
      "links": [],
      "minSpan": 24,
      "mode": "html",
      "title": "",
      "transparent": true,
      "type": "text"
    },
    {
      "aliasColors": {},
      "bars": false,
      "dashLength": 10,
      "dashes": false,
      "datasource": "prometheus",
      "decimals": null,
      "editable": true,
      "error": false,
      "fill": 1,
      "grid": {},
      "gridPos": {
        "h": 7,
        "w": 8,
        "x": 0,
        "y": 37
      },
      "id": 58,
      "legend": {
        "avg": false,
        "current": false,
        "max": false,
        "min": false,
        "show": false,
        "total": false,
        "values": false
      },
      "lines": true,
      "linewidth": 2,
      "links": [],
      "minSpan": 8,
      "nullPointMode": "connected",
      "percentage": false,
      "pointradius": 5,
      "points": false,
      "renderer": "flot",
      "seriesOverrides": [],
      "spaceLength": 10,
      "stack": false,
      "steppedLine": false,
      "targets": [
        {
          "expr": "jvm:heap:used{instance=~\"$instance\"}",
          "intervalFactor": 1,
          "legendFormat": "{{instance}}",
          "refId": "A",
          "step": 2
        }
      ],
      "thresholds": [],
      "timeFrom": null,
      "timeShift": null,
      "title": "Bytes Used",
      "tooltip": {
        "msResolution": false,
        "shared": true,
        "sort": 2,
        "value_type": "cumulative"
      },
      "type": "graph",
      "xaxis": {
        "buckets": null,
        "mode": "time",
        "name": null,
        "show": true,
        "values": []
      },
      "yaxes": [
        {
          "format": "bytes",
          "label": null,
          "logBase": 1,
          "max": null,
          "min": null,
          "show": true
        },
        {
          "format": "short",
          "label": null,
          "logBase": 1,
          "max": null,
          "min": null,
          "show": false
        }
      ],
      "yaxis": {
        "align": false,
        "alignLevel": null
      }
    },
    {
      "aliasColors": {},
      "bars": false,
      "dashLength": 10,
      "dashes": false,
      "datasource": "prometheus",
      "decimals": null,
      "editable": true,
      "error": false,
      "fill": 1,
      "grid": {},
      "gridPos": {
        "h": 7,
        "w": 8,
        "x": 8,
        "y": 37
      },
      "id": 69,
      "legend": {
        "avg": false,
        "current": false,
        "max": false,
        "min": false,
        "show": false,
        "total": false,
        "values": false
      },
      "lines": true,
      "linewidth": 2,
      "links": [],
      "minSpan": 8,
      "nullPointMode": "connected",
      "percentage": false,
      "pointradius": 5,
      "points": false,
      "renderer": "flot",
      "seriesOverrides": [],
      "spaceLength": 10,
      "stack": false,
      "steppedLine": false,
      "targets": [
        {
          "expr": "jvm:heap:used{instance=~\"$instance\"} / jvm:heap:max{instance=~\"$instance\"}",
          "intervalFactor": 1,
          "legendFormat": "{{instance}}",
          "refId": "A",
          "step": 2
        }
      ],
      "thresholds": [],
      "timeFrom": null,
      "timeShift": null,
      "title": "% Used",
      "tooltip": {
        "msResolution": false,
        "shared": true,
        "sort": 2,
        "value_type": "cumulative"
      },
      "type": "graph",
      "xaxis": {
        "buckets": null,
        "mode": "time",
        "name": null,
        "show": true,
        "values": []
      },
      "yaxes": [
        {
          "format": "percentunit",
          "label": null,
          "logBase": 1,
          "max": null,
          "min": null,
          "show": true
        },
        {
          "format": "short",
          "label": null,
          "logBase": 1,
          "max": null,
          "min": null,
          "show": false
        }
      ],
      "yaxis": {
        "align": false,
        "alignLevel": null
      }
    },
    {
      "aliasColors": {},
      "bars": false,
      "dashLength": 10,
      "dashes": false,
      "datasource": "prometheus",
      "decimals": null,
      "editable": true,
      "error": false,
      "fill": 1,
      "grid": {},
      "gridPos": {
        "h": 7,
        "w": 8,
        "x": 16,
        "y": 37
      },
      "id": 70,
      "legend": {
        "avg": false,
        "current": false,
        "max": false,
        "min": false,
        "show": false,
        "total": false,
        "values": false
      },
      "lines": true,
      "linewidth": 2,
      "links": [],
      "minSpan": 8,
      "nullPointMode": "connected",
      "percentage": false,
      "pointradius": 5,
      "points": false,
      "renderer": "flot",
      "seriesOverrides": [],
      "spaceLength": 10,
      "stack": false,
      "steppedLine": false,
      "targets": [
        {
          "expr": "jvm:gc:eden:pause_msec{quantile=\"0.5\",instance=~\"$instance\"}",
          "intervalFactor": 1,
          "legendFormat": "p50 {{instance}}",
          "refId": "A",
          "step": 2
        },
        {
          "expr": "jvm:gc:eden:pause_msec{quantile=\"0.9\",instance=~\"$instance\"}",
          "intervalFactor": 1,
          "legendFormat": "p99 {{instance}}",
          "refId": "B",
          "step": 2
        },
        {
          "expr": "jvm:gc:eden:pause_msec{quantile=\"0.99\",instance=~\"$instance\"}",
          "intervalFactor": 1,
          "legendFormat": "p99 {{instance}}",
          "refId": "C",
          "step": 2
        }
      ],
      "thresholds": [],
      "timeFrom": null,
      "timeShift": null,
      "title": "GC Pauses (Eden)",
      "tooltip": {
        "msResolution": false,
        "shared": true,
        "sort": 2,
        "value_type": "cumulative"
      },
      "type": "graph",
      "xaxis": {
        "buckets": null,
        "mode": "time",
        "name": null,
        "show": true,
        "values": []
      },
      "yaxes": [
        {
          "format": "ms",
          "label": "",
          "logBase": 1,
          "max": null,
          "min": null,
          "show": true
        },
        {
          "format": "short",
          "label": null,
          "logBase": 1,
          "max": null,
          "min": null,
          "show": false
        }
      ],
      "yaxis": {
        "align": false,
        "alignLevel": null
      }
    },
    {
      "content": "<div class=\"text-center dashboard-header\">\n  <span>RESOURCES</span>\n</div>\n",
      "editable": true,
      "error": false,
      "gridPos": {
        "h": 3,
        "w": 24,
        "x": 0,
        "y": 44
      },
      "height": "1px",
      "id": 33,
      "links": [],
      "minSpan": 24,
      "mode": "html",
      "title": "",
      "transparent": true,
      "type": "text"
    },
    {
      "aliasColors": {},
      "bars": false,
      "dashLength": 10,
      "dashes": false,
      "datasource": "prometheus",
      "decimals": null,
      "editable": true,
      "error": false,
      "fill": 1,
      "grid": {},
      "gridPos": {
        "h": 7,
        "w": 8,
        "x": 0,
        "y": 47
      },
      "id": 34,
      "legend": {
        "avg": false,
        "current": false,
        "max": false,
        "min": false,
        "show": false,
        "total": false,
        "values": false
      },
      "lines": true,
      "linewidth": 2,
      "links": [],
      "minSpan": 8,
      "nullPointMode": "connected",
      "percentage": false,
      "pointradius": 5,
      "points": false,
      "renderer": "flot",
      "seriesOverrides": [],
      "spaceLength": 10,
      "stack": false,
      "steppedLine": false,
      "targets": [
        {
          "expr": "jvm:thread:count{instance=~\"$instance\"}",
          "intervalFactor": 1,
          "legendFormat": "{{instance}}",
          "refId": "A",
          "step": 2
        }
      ],
      "thresholds": [],
      "timeFrom": null,
      "timeShift": null,
      "title": "Threads",
      "tooltip": {
        "msResolution": false,
        "shared": true,
        "sort": 2,
        "value_type": "cumulative"
      },
      "type": "graph",
      "xaxis": {
        "buckets": null,
        "mode": "time",
        "name": null,
        "show": true,
        "values": []
      },
      "yaxes": [
        {
          "format": "none",
          "label": null,
          "logBase": 1,
          "max": null,
          "min": null,
          "show": true
        },
        {
          "format": "short",
          "label": null,
          "logBase": 1,
          "max": null,
          "min": null,
          "show": false
        }
      ],
      "yaxis": {
        "align": false,
        "alignLevel": null
      }
    },
    {
      "aliasColors": {},
      "bars": false,
      "dashLength": 10,
      "dashes": false,
      "datasource": "prometheus",
      "decimals": null,
      "editable": true,
      "error": false,
      "fill": 1,
      "grid": {},
      "gridPos": {
        "h": 7,
        "w": 8,
        "x": 8,
        "y": 47
      },
      "id": 60,
      "legend": {
        "avg": false,
        "current": false,
        "max": false,
        "min": false,
        "show": false,
        "total": false,
        "values": false
      },
      "lines": true,
      "linewidth": 2,
      "links": [],
      "minSpan": 8,
      "nullPointMode": "connected",
      "percentage": false,
      "pointradius": 5,
      "points": false,
      "renderer": "flot",
      "seriesOverrides": [],
      "spaceLength": 10,
      "stack": false,
      "steppedLine": false,
      "targets": [
        {
          "expr": "jvm:fd_count{instance=~\"$instance\"}",
          "intervalFactor": 1,
          "legendFormat": "{{instance}}",
          "refId": "A",
          "step": 2
        }
      ],
      "thresholds": [],
      "timeFrom": null,
      "timeShift": null,
      "title": "File Descriptors",
      "tooltip": {
        "msResolution": false,
        "shared": true,
        "sort": 2,
        "value_type": "cumulative"
      },
      "type": "graph",
      "xaxis": {
        "buckets": null,
        "mode": "time",
        "name": null,
        "show": true,
        "values": []
      },
      "yaxes": [
        {
          "format": "none",
          "label": "",
          "logBase": 1,
          "max": null,
          "min": null,
          "show": true
        },
        {
          "format": "short",
          "label": null,
          "logBase": 1,
          "max": null,
          "min": null,
          "show": false
        }
      ],
      "yaxis": {
        "align": false,
        "alignLevel": null
      }
    },
    {
      "aliasColors": {},
      "bars": false,
      "dashLength": 10,
      "dashes": false,
      "datasource": "prometheus",
      "decimals": null,
      "editable": true,
      "error": false,
      "fill": 1,
      "grid": {},
      "gridPos": {
        "h": 7,
        "w": 8,
        "x": 16,
        "y": 47
      },
      "id": 55,
      "legend": {
        "avg": false,
        "current": false,
        "max": false,
        "min": false,
        "show": false,
        "total": false,
        "values": false
      },
      "lines": true,
      "linewidth": 2,
      "links": [],
      "minSpan": 8,
      "nullPointMode": "connected",
      "percentage": false,
      "pointradius": 5,
      "points": false,
      "renderer": "flot",
      "seriesOverrides": [],
      "spaceLength": 10,
      "stack": false,
      "steppedLine": false,
      "targets": [
        {
          "expr": "jvm:uptime{instance=~\"$instance\"}",
          "intervalFactor": 1,
          "legendFormat": "{{instance}}",
          "refId": "A",
          "step": 2
        }
      ],
      "thresholds": [],
      "timeFrom": null,
      "timeShift": null,
      "title": "Uptime",
      "tooltip": {
        "msResolution": false,
        "shared": true,
        "sort": 2,
        "value_type": "cumulative"
      },
      "type": "graph",
      "xaxis": {
        "buckets": null,
        "mode": "time",
        "name": null,
        "show": true,
        "values": []
      },
      "yaxes": [
        {
          "format": "ms",
          "label": null,
          "logBase": 1,
          "max": null,
          "min": null,
          "show": true
        },
        {
          "format": "short",
          "label": null,
          "logBase": 1,
          "max": null,
          "min": null,
          "show": false
        }
      ],
      "yaxis": {
        "align": false,
        "alignLevel": null
      }
    }
  ],
  "refresh": "5s",
  "schemaVersion": 16,
  "style": "dark",
  "tags": [],
  "templating": {
    "list": [
      {
        "allValue": null,
        "current": {},
        "datasource": "prometheus",
        "hide": 0,
        "includeAll": true,
        "label": null,
        "multi": true,
        "name": "instance",
        "options": [],
        "query": "label_values(instance)",
        "refresh": 2,
        "regex": "",
        "sort": 1,
        "tagValuesQuery": "",
        "tags": [],
        "tagsQuery": "",
        "type": "query",
        "useTags": false
      }
    ]
  },
  "time": {
    "from": "now-5m",
    "to": "now"
  },
  "timepicker": {
    "refresh_intervals": [
      "5s",
      "10s",
      "30s",
      "1m",
      "5m",
      "15m",
      "30m",
      "1h",
      "2h",
      "1d"
    ],
    "time_options": [
      "5m",
      "15m",
      "1h",
      "6h",
      "12h",
      "24h",
      "2d",
      "7d",
      "30d"
    ]
  },
  "timezone": "browser",
  "title": "linkerd-health",
  "uid": "SgkOAj5iz",
  "version": 1
}
